pkiexpress/__init__.py
pkiexpress/auth_complete_result.py
pkiexpress/auth_start_result.py
pkiexpress/authentication.py
pkiexpress/base_signer.py
pkiexpress/cades_signature.py
pkiexpress/cades_signature_editor.py
pkiexpress/cades_signature_explorer.py
pkiexpress/cades_signature_starter.py
pkiexpress/cades_signer.py
pkiexpress/certificate_reader.py
pkiexpress/check_service_result.py
pkiexpress/color.py
pkiexpress/commitment_type.py
pkiexpress/digest_algorithm.py
pkiexpress/digest_algorithm_and_value.py
pkiexpress/discover_services_result.py
pkiexpress/installation_not_found_error.py
pkiexpress/key_generation_result.py
pkiexpress/key_generator.py
pkiexpress/name.py
pkiexpress/oids.py
pkiexpress/pades_certification_level.py
pkiexpress/pades_horizontal_align.py
pkiexpress/pades_measurement_units.py
pkiexpress/pades_signature.py
pkiexpress/pades_signature_explorer.py
pkiexpress/pades_signature_starter.py
pkiexpress/pades_signer.py
pkiexpress/pades_signer_info.py
pkiexpress/pades_timestamper.py
pkiexpress/pades_visual_rectangle.py
pkiexpress/pdf_container_definition.py
pkiexpress/pdf_helper.py
pkiexpress/pdf_mark.py
pkiexpress/pdf_mark_element.py
pkiexpress/pdf_mark_element_type.py
pkiexpress/pdf_mark_image.py
pkiexpress/pdf_mark_image_element.py
pkiexpress/pdf_mark_page_options.py
pkiexpress/pdf_mark_qr_code_element.py
pkiexpress/pdf_mark_text_element.py
pkiexpress/pdf_marker.py
pkiexpress/pdf_text_section.py
pkiexpress/pdf_text_style.py
pkiexpress/pk_algorithm.py
pkiexpress/pk_certificate.py
pkiexpress/pkcs12_certificate.py
pkiexpress/pkcs12_generation_result.py
pkiexpress/pkcs12_generator.py
pkiexpress/pki_brazil_certificate_fields.py
pkiexpress/pki_express_config.py
pkiexpress/pki_express_operator.py
pkiexpress/pki_italy_certificate_fields.py
pkiexpress/resource_content_or_reference.py
pkiexpress/signature_algorithm_and_value.py
pkiexpress/signature_explorer.py
pkiexpress/signature_finisher.py
pkiexpress/signature_policy_identifier.py
pkiexpress/signature_starter.py
pkiexpress-1.10.4.dist-info/METADATA
pkiexpress-1.10.4.dist-info/WHEEL
pkiexpress-1.10.4.dist-info/top_level.txt
pkiexpress-1.10.4.dist-info/RECORD
