Metadata-Version: 2.1
Name: pkiexpress
Version: 1.10.4
Summary: Classes to consume PKI Express
Home-page: https://github.com/LacunaSoftware/PkiExpressPython
Author: Leonardo Pignataro
Author-email: leonardop@lacunasoftware.com
Keywords: python pki express certificate digital signature x509
Classifier: Intended Audience :: Developers
Classifier: Intended Audience :: Financial and Insurance Industry
Classifier: Intended Audience :: Information Technology
Classifier: Programming Language :: Python
Classifier: Programming Language :: Python :: 2.7
Classifier: Programming Language :: Python :: 3.3
Classifier: Programming Language :: Python :: 3.4
Classifier: Programming Language :: Python :: 3.5
Classifier: Programming Language :: Python :: 3.6
Classifier: Operating System :: OS Independent
Classifier: Topic :: Security
Classifier: Topic :: Security :: Cryptography
Classifier: Topic :: Software Development :: Libraries :: Python Modules
